bbrl_algos/__init__.py
bbrl_algos/_version.py
bbrl_algos/algos/__init__.py
bbrl_algos/algos/a2c/a2c.py
bbrl_algos/algos/a2c/a2c_rocket_lander.py
bbrl_algos/algos/a2c/a2c_swimmer.py
bbrl_algos/algos/a2c/configs/a2c_cartpole.yaml
bbrl_algos/algos/a2c/configs/a2c_cartpolecontinuous.yaml
bbrl_algos/algos/a2c/configs/a2c_pendulum.yaml
bbrl_algos/algos/a2c/configs/a2c_rocket_lander.yaml
bbrl_algos/algos/a2c/configs/a2c_swimmer.yaml
bbrl_algos/algos/cem/cem.py
bbrl_algos/algos/cem/cem_lstm.py
bbrl_algos/algos/cem/configs/cem_cartpole.yaml
bbrl_algos/algos/cem/configs/cem_mountain_car.yaml
bbrl_algos/algos/cem/configs/cem_swimmer_best.yaml
bbrl_algos/algos/cem/configs/cem_swimmer_optuna.yaml
bbrl_algos/algos/ddpg/ddpg.py
bbrl_algos/algos/ddpg/ddpg_stats.py
bbrl_algos/algos/ddpg/configs/ddpg_cartpole.yaml
bbrl_algos/algos/ddpg/configs/ddpg_lunar_lander_continuous.yaml
bbrl_algos/algos/ddpg/configs/ddpg_pendulum.yaml
bbrl_algos/algos/ddpg/configs/ddpg_pendulum_optimise.yaml
bbrl_algos/algos/ddpg/configs/ddpg_pendulum_optuna.yaml
bbrl_algos/algos/dqn/dqn.py
bbrl_algos/algos/dqn/dqn_maze.py
bbrl_algos/algos/dqn/configs/cartpole_wandb_no_optuna.yaml
bbrl_algos/algos/dqn/configs/cartpole_wandb_optuna.yaml
bbrl_algos/algos/dqn/configs/cartpole_wandb_optuna_choices.yaml
bbrl_algos/algos/dqn/configs/continuous_maze.yaml
bbrl_algos/algos/ppo/ppo_clip.py
bbrl_algos/algos/ppo/ppo_clip_full.py
bbrl_algos/algos/ppo/ppo_penalty.py
bbrl_algos/algos/ppo/configs/ppo_cartpole.yaml
bbrl_algos/algos/ppo/configs/ppo_cartpole_continuous.yaml
bbrl_algos/algos/ppo/configs/ppo_lunarlander.yaml
bbrl_algos/algos/ppo/configs/ppo_lunarlander_continuous.yaml
bbrl_algos/algos/ppo/configs/ppo_pendulum.yaml
bbrl_algos/algos/ppo/configs/ppo_single_state.yaml
bbrl_algos/algos/ppo/configs/ppo_swimmer.yaml
bbrl_algos/algos/reinforce/learn_value_mc.py
bbrl_algos/algos/reinforce/reinforce_full.py
bbrl_algos/algos/reinforce/reinforce_probagent.py
bbrl_algos/algos/reinforce/configs/reinforce_cartpole.yaml
bbrl_algos-0.0.2.dist-info/LICENSE
bbrl_algos-0.0.2.dist-info/METADATA
bbrl_algos-0.0.2.dist-info/WHEEL
bbrl_algos-0.0.2.dist-info/top_level.txt
bbrl_algos-0.0.2.dist-info/RECORD
